LICENSE
MANIFEST.in
README.rst
setup.py
django_servee_gallery.egg-info/PKG-INFO
django_servee_gallery.egg-info/SOURCES.txt
django_servee_gallery.egg-info/dependency_links.txt
django_servee_gallery.egg-info/not-zip-safe
django_servee_gallery.egg-info/requires.txt
django_servee_gallery.egg-info/top_level.txt
servee_gallery/__init__.py
servee_gallery/admin.py
servee_gallery/models.py
servee_gallery/servee_registry.py
servee_gallery/settings.py
servee_gallery/templates/inlines/servee_gallery_gallery.html
servee_gallery/templates/servee/wysiwyg/insert/servee_gallery/_add.html
servee_gallery/templates/servee/wysiwyg/insert/servee_gallery/_add_image.html
servee_gallery/templates/servee/wysiwyg/insert/servee_gallery/_detail.html
servee_gallery/templates/servee/wysiwyg/insert/servee_gallery/_list.html
servee_gallery/templates/servee/wysiwyg/insert/servee_gallery/_render.html