Metadata-Version: 1.0
Name: django-servee-gallery
Version: 0.2
Summary: Document Plugin for django-servee
Home-page: http://github.com/servee/django-servee-gallery/
Author: Issac Kelly
Author-email: issac@servee.com
License: BSD
Platform: UNKNOWN
Classifier: Development Status :: 3 - Alpha
Classifier: Framework :: Django
Classifier: Intended Audience :: Developers
Classifier: License :: OSI Approved :: BSD License
Classifier: Operating System :: OS Independent
Classifier: Programming Language :: Python
Classifier: Topic :: Internet :: WWW/HTTP
